MANIFEST.in
README.rst
setup.cfg
setup.py
Products/__init__.py
Products.FacultyStaffDirectory.egg-info/PKG-INFO
Products.FacultyStaffDirectory.egg-info/SOURCES.txt
Products.FacultyStaffDirectory.egg-info/dependency_links.txt
Products.FacultyStaffDirectory.egg-info/entry_points.txt
Products.FacultyStaffDirectory.egg-info/namespace_packages.txt
Products.FacultyStaffDirectory.egg-info/not-zip-safe
Products.FacultyStaffDirectory.egg-info/requires.txt
Products.FacultyStaffDirectory.egg-info/top_level.txt
Products/FacultyStaffDirectory/Classification.py
Products/FacultyStaffDirectory/Committee.py
Products/FacultyStaffDirectory/CommitteeMembership.py
Products/FacultyStaffDirectory/CommitteesFolder.py
Products/FacultyStaffDirectory/Course.py
Products/FacultyStaffDirectory/Department.py
Products/FacultyStaffDirectory/DepartmentalMembership.py
Products/FacultyStaffDirectory/FacultyStaffDirectory.py
Products/FacultyStaffDirectory/Person.py
Products/FacultyStaffDirectory/PersonGrouping.py
Products/FacultyStaffDirectory/SpecialtiesFolder.py
Products/FacultyStaffDirectory/Specialty.py
Products/FacultyStaffDirectory/SpecialtyInformation.py
Products/FacultyStaffDirectory/__init__.py
Products/FacultyStaffDirectory/config.py
Products/FacultyStaffDirectory/configure.zcml
Products/FacultyStaffDirectory/extenderInstallation.py
Products/FacultyStaffDirectory/migrations.py
Products/FacultyStaffDirectory/permissions.py
Products/FacultyStaffDirectory/profiles.zcml
Products/FacultyStaffDirectory/refresh.txt
Products/FacultyStaffDirectory/relations.xml
Products/FacultyStaffDirectory/setuphandlers.py
Products/FacultyStaffDirectory/sharing.py
Products/FacultyStaffDirectory/upgrades.zcml
Products/FacultyStaffDirectory/utility.py
Products/FacultyStaffDirectory/validators.py
Products/FacultyStaffDirectory/Extensions/Install.py
Products/FacultyStaffDirectory/Extensions/__init__.py
Products/FacultyStaffDirectory/events/__init__.py
Products/FacultyStaffDirectory/events/configure.zcml
Products/FacultyStaffDirectory/events/events.py
Products/FacultyStaffDirectory/events/facultystaffdirectorytool.py
Products/FacultyStaffDirectory/events/person.py
Products/FacultyStaffDirectory/examples/Products.MobilePhoneExtender/setup.py
Products/FacultyStaffDirectory/examples/Products.MobilePhoneExtender/Products/__init__.py
Products/FacultyStaffDirectory/examples/Products.MobilePhoneExtender/Products/MobilePhoneExtender/README.txt
