Metadata-Version: 1.1
Name: Products.FacultyStaffDirectory
Version: 5.0
Summary: Provides content types for creating and organizing personnel directories within educational institutions. Integrates with Plone's users and groups infrastructure and supports an extensibility framework for custom requirements.
Home-page: https://github.com/collective/Products.FacultyStaffDirectory
Author: originally by WebLion Group, The Pennsylvania State University
Author-email: UNKNOWN
License: GPL
Platform: UNKNOWN
Classifier: Framework :: Plone
Classifier: Framework :: Plone :: 4.0
Classifier: Framework :: Plone :: 4.1
Classifier: Framework :: Plone :: 4.2
Classifier: Framework :: Plone :: 4.3
Classifier: Framework :: Plone :: 5.0
Classifier: Programming Language :: Python
Classifier: Topic :: Software Development :: Libraries :: Python Modules
Classifier: License :: OSI Approved :: GNU General Public License v2 or later (GPLv2+)
